{"schema_version":1,"generated_at":"2026-07-24T06:20:38.948122+00:00","forecast_reference_id":8469,"status":"success","fresh":true,"historical":false,"data_source":"smn_modern_forecast","fetched_at":"2026-07-24T06:16:43.005782+00:00","payload":{"updated":"2026-07-23T17:36:37-03:00","location":{"id":8469,"name":"Bella Vista","department":"Tilcara","province":"Jujuy","type":"Paraje","coord":{"lon":-65.4196,"lat":-23.658}},"type":"location","forecast":[{"date":"2026-07-24","temp_min":4.0,"temp_max":17.0,"humidity_min":8.0,"humidity_max":24.0,"early_morning":{"humidity":24.0,"rain_prob_range":[0,0],"gust_range":[42,50],"temperature":6.0,"visibility":"Buena","rain06h":0.0,"weather":{"description":"Parcialmente nublado","id":25},"wind":{"direction":"O","deg":292.5,"speed_range":[13,22]},"river":null,"border":null},"morning":{"humidity":17.0,"rain_prob_range":[0,0],"gust_range":[42,50],"temperature":4.0,"visibility":"Buena","rain06h":0.0,"weather":{"description":"Ligeramente nublado","id":13},"wind":{"direction":"O","deg":292.5,"speed_range":[23,31]},"river":null,"border":null},"afternoon":{"humidity":8.0,"rain_prob_range":[0,0],"gust_range":[42,50],"temperature":17.0,"visibility":"Buena","rain06h":0.0,"weather":{"description":"Ligeramente nublado","id":13},"wind":{"direction":"O","deg":292.5,"speed_range":[23,31]},"river":null,"border":null},"night":{"humidity":16.0,"rain_prob_range":[0,0],"gust_range":null,"temperature":13.0,"visibility":"Buena","rain06h":0.0,"weather":{"description":"Despejado","id":3},"wind":{"direction":"O","deg":292.5,"speed_range":[7,12]},"river":null,"border":null}},{"date":"2026-07-25","temp_min":2.0,"temp_max":18.0,"humidity_min":8.0,"humidity_max":19.0,"early_morning":{"humidity":11.0,"rain_prob_range":[0,0],"gust_range":null,"temperature":4.0,"visibility":"Buena","rain06h":0.0,"weather":{"description":"Algo nublado","id":19},"wind":{"direction":"O","deg":270.0,"speed_range":[7,12]},"river":null,"border":null},"morning":{"humidity":19.0,"rain_prob_range":[0,0],"gust_range":[42,50],"temperature":2.0,"visibility":"Buena","rain06h":0.0,"weather":{"description":"Ligeramente nublado","id":13},"wind":{"direction":"O","deg":292.5,"speed_range":[23,31]},"river":null,"border":null},"afternoon":{"humidity":13.0,"rain_prob_range":[0,0],"gust_range":null,"temperature":18.0,"visibility":"Buena","rain06h":0.0,"weather":{"description":"Ligeramente nublado","id":13},"wind":{"direction":"O","deg":292.5,"speed_range":[23,31]},"river":null,"border":null},"night":{"humidity":8.0,"rain_prob_range":[0,0],"gust_range":null,"temperature":15.0,"visibility":"Buena","rain06h":0.0,"weather":{"description":"Ligeramente nublado","id":13},"wind":{"direction":"O","deg":270.0,"speed_range":[7,12]},"river":null,"border":null}},{"date":"2026-07-26","temp_min":2.0,"temp_max":17.0,"humidity_min":5.0,"humidity_max":7.0,"early_morning":null,"morning":{"humidity":7.0,"rain_prob_range":[0,0],"gust_range":null,"temperature":2.0,"visibility":"Buena","rain06h":0.0,"weather":{"description":"Algo nublado","id":19},"wind":{"direction":"O","deg":292.5,"speed_range":[23,31]},"river":null,"border":null},"afternoon":{"humidity":5.0,"rain_prob_range":[0,0],"gust_range":null,"temperature":17.0,"visibility":"Buena","rain06h":0.0,"weather":{"description":"Algo nublado","id":19},"wind":{"direction":"O","deg":292.5,"speed_range":[23,31]},"river":null,"border":null},"night":null},{"date":"2026-07-27","temp_min":4.0,"temp_max":21.0,"humidity_min":5.0,"humidity_max":10.0,"early_morning":null,"morning":{"humidity":10.0,"rain_prob_range":[0,0],"gust_range":null,"temperature":4.0,"visibility":"Buena","rain06h":0.0,"weather":{"description":"Algo nublado","id":19},"wind":{"direction":"O","deg":292.5,"speed_range":[23,31]},"river":null,"border":null},"afternoon":{"humidity":5.0,"rain_prob_range":[0,0],"gust_range":null,"temperature":21.0,"visibility":"Buena","rain06h":0.0,"weather":{"description":"Algo nublado","id":19},"wind":{"direction":"O","deg":292.5,"speed_range":[23,31]},"river":null,"border":null},"night":null},{"date":"2026-07-28","temp_min":5.0,"temp_max":18.0,"humidity_min":7.0,"humidity_max":12.0,"early_morning":null,"morning":{"humidity":12.0,"rain_prob_range":[0,0],"gust_range":null,"temperature":5.0,"visibility":"Buena","rain06h":0.0,"weather":{"description":"Algo nublado","id":19},"wind":{"direction":"O","deg":292.5,"speed_range":[23,31]},"river":null,"border":null},"afternoon":{"humidity":7.0,"rain_prob_range":[0,0],"gust_range":null,"temperature":18.0,"visibility":"Buena","rain06h":0.0,"weather":{"description":"Algo nublado","id":19},"wind":{"direction":"O","deg":292.5,"speed_range":[23,31]},"river":null,"border":null},"night":null},{"date":"2026-07-29","temp_min":5.0,"temp_max":18.0,"humidity_min":8.0,"humidity_max":16.0,"early_morning":null,"morning":{"humidity":16.0,"rain_prob_range":[0,0],"gust_range":null,"temperature":5.0,"visibility":"Buena","rain06h":0.0,"weather":{"description":"Parcialmente nublado","id":25},"wind":{"direction":"O","deg":292.5,"speed_range":[23,31]},"river":null,"border":null},"afternoon":{"humidity":8.0,"rain_prob_range":[0,0],"gust_range":null,"temperature":18.0,"visibility":"Buena","rain06h":0.0,"weather":{"description":"Parcialmente nublado","id":25},"wind":{"direction":"O","deg":292.5,"speed_range":[7,12]},"river":null,"border":null},"night":null},{"date":"2026-07-30","temp_min":3.0,"temp_max":15.0,"humidity_min":9.0,"humidity_max":9.0,"early_morning":null,"morning":{"humidity":null,"rain_prob_range":[0,0],"gust_range":null,"temperature":3.0,"visibility":"Buena","rain06h":null,"weather":{"description":"Parcialmente nublado","id":25},"wind":{"direction":"O","deg":270.0,"speed_range":[7,12]},"river":null,"border":null},"afternoon":{"humidity":9.0,"rain_prob_range":[0,0],"gust_range":[42,50],"temperature":15.0,"visibility":"Buena","rain06h":0.0,"weather":{"description":"Parcialmente nublado","id":25},"wind":{"direction":"NO","deg":315.0,"speed_range":[13,22]},"river":null,"border":null},"night":null}],"source":"smn_modern_forecast","historical":false}}
